{
  "BlockType": {
    "DrawType": "Model",
    "CustomModel": "Resources/Models/Carte Chapitre Dark Castle.blockymodel",
    "CustomModelTexture": [
      {
        "Texture": "Resources/Textures/Chapitre/30.png"
      }
    ],
    "VariantRotation": "NESW",
    "Material": "Solid",
    "Support": {
      "BlockSides": [
        {
          "FaceType": "Full",
          "Support": "Required"
        }
      ]
    },
    "Gathering": {
      "Breaking": {
        "GatherType": "SoftBlocks",
        "ItemId": "Card_Chapter24_Hand"
      }
    },
    "CustomModelAnimation": "Resources/Animations/DarkCastle_Chapitre_Animation.blockyanim",
    "HitboxType": "Hitbox_Cards_Big"
  },
  "IconProperties": {
    "Scale": 0.5,
    "Rotation": [
      0,
      0,
      0
    ],
    "Translation": [
      -3,
      -55
    ]
  },
  "PlayerAnimationsId": "Block",
  "Icon": "Icons/ItemsGenerated/Card_Chapter24.png",
  "TranslationProperties": {
    "Name": "server.items.DarkCaslte_Chapter.name"
  },
  "Quality": "Developer"
}
